consolidatewheels/__init__.py
consolidatewheels/__main__.py
consolidatewheels/consolidate_linux.py
consolidatewheels/consolidate_osx.py
consolidatewheels/consolidate_win.py
consolidatewheels/dedupe.py
consolidatewheels/main.py
consolidatewheels/wheelsfunc.py
consolidatewheels-0.4.dist-info/LICENSE
consolidatewheels-0.4.dist-info/METADATA
consolidatewheels-0.4.dist-info/WHEEL
consolidatewheels-0.4.dist-info/entry_points.txt
consolidatewheels-0.4.dist-info/top_level.txt
consolidatewheels-0.4.dist-info/RECORD
