Metadata-Version: 2.1
Name: consolidatewheels
Version: 0.4
Summary: Consolidates the shared object dependencies across multiple wheels
Author-email: Alessandro Molina <amol@turbogears.org>
License: MIT
Classifier: Programming Language :: Python :: 3
Requires-Python: >=3.7
License-File: LICENSE
Requires-Dist: wheel
Requires-Dist: pkginfo
Requires-Dist: pefile
Provides-Extra: testing
Requires-Dist: pytest (>=3.4) ; extra == 'testing'
Requires-Dist: pytest-cov ; extra == 'testing'
